makeFlowerPolygons/__init__.py
makeFlowerPolygons/breakSpots.py
makeFlowerPolygons/flowerPetal.py
makeFlowerPolygons/geojsonIO.py
makeFlowerPolygons/get_spots.py
makeFlowerPolygons/get_zones.py
makeFlowerPolygons/makePDFs.py
makeFlowerPolygons/manZoneCaller.py
makeFlowerPolygons/spotMarker.py
makeFlowerPolygons_dcthom-0.0.28.dist-info/LICENSE
makeFlowerPolygons_dcthom-0.0.28.dist-info/METADATA
makeFlowerPolygons_dcthom-0.0.28.dist-info/WHEEL
makeFlowerPolygons_dcthom-0.0.28.dist-info/top_level.txt
makeFlowerPolygons_dcthom-0.0.28.dist-info/RECORD
