Metadata-Version: 2.1
Name: makeFlowerPolygons-dcthom
Version: 0.0.28
Summary: Cooley lab tools for digitizing and analyzing Mimulus spotting patterns
Home-page: https://github.com/danchurch/mimulusSpeckling
Author: Daniel Thomas
Author-email: thomasdc@whitman.edu
License: UNKNOWN
Platform: UNKNOWN
Classifier: Programming Language :: Python :: 3
Classifier: License :: OSI Approved :: GNU General Public License v3 or later (GPLv3+)
Classifier: Development Status :: 3 - Alpha
Classifier: Operating System :: POSIX :: Linux
